dnswrapper/__init__.py
dnswrapper/provider/__init__.py
dnswrapper/provider/aws/client.py
dnswrapper/provider/aws/zonemanager.py
dnswrapper/provider/aws/response/list_hosted_zones.py
dnswrapper/provider/aws/response/list_resource_record_sets.py
dnswrapper/provider/error/awsresponse.py
dnswrapper/provider/error/zonecontrol.py
dnswrapper/record/arecord.py
dnswrapper/record/record.py
dnswrapper/record/txt_record.py
dnswrapper/resolvers/__init__.py
dnswrapper/resolvers/local_client.py
dnswrapper/resolvers/local_resolver.py
dnswrapper/resolvers/lookup_error.py
dnswrapper-0.0.4.dist-info/METADATA
dnswrapper-0.0.4.dist-info/WHEEL
dnswrapper-0.0.4.dist-info/top_level.txt
dnswrapper-0.0.4.dist-info/RECORD
