Metadata-Version: 2.1
Name: dnswrapper
Version: 0.0.4
Summary: A small example package
Author-email: Example Author <author@example.com>
Classifier: Programming Language :: Python :: 3
Classifier: License :: OSI Approved :: MIT License
Classifier: Operating System :: OS Independent
Requires-Python: >=3.7
Requires-Dist: dnspython
Requires-Dist: boto3
